betsapi/__init__.py
betsapi/baseapi.py
betsapi/bet365.py
betsapi/betfair.py
betsapi/betway.py
betsapi/bwin.py
betsapi/events.py
betsapi/results.py
betsapi/sbobet.py
betsapi-1.0.1.dist-info/DESCRIPTION.rst
betsapi-1.0.1.dist-info/METADATA
betsapi-1.0.1.dist-info/RECORD
betsapi-1.0.1.dist-info/WHEEL
betsapi-1.0.1.dist-info/metadata.json
betsapi-1.0.1.dist-info/top_level.txt
