Metadata-Version: 2.0
Name: betsapi
Version: 1.0.1
Summary: betsapi python SDK
Home-page: https://github.com/qwqmeow/betsapi-python
Author: meoww
Author-email: i@meoww.app
License: UNKNOWN
Download-URL: https://github.com/qwqmeow/betsapi-python/releases
Keywords: bet,api,odds
Platform: UNKNOWN
Requires-Dist: requests
